linear_regression/__init__.py
linear_regression/metrics.py
linear_regression/preprocessing.py
linear_regression/utils.py
linear_regression/models/__init__.py
linear_regression/models/linear_regression.py
linear_regression/models/polynomial_regression.py
linreg_from_scratch-0.2.1.dist-info/licenses/LICENSE
linreg_from_scratch-0.2.1.dist-info/METADATA
linreg_from_scratch-0.2.1.dist-info/WHEEL
linreg_from_scratch-0.2.1.dist-info/top_level.txt
linreg_from_scratch-0.2.1.dist-info/RECORD
