Metadata-Version: 2.4
Name: linreg-from-scratch
Version: 0.2.1
Summary: A clean implementation of linear regression algorithms from scratch
Author-email: Illias <illiasdadashov313@gmail.com>
License: MIT
Project-URL: Homepage, https://github.com/illo_one_go/linear-regression-from-scratch
Project-URL: Bug Tracker, https://github.com/illo_one_go/linear-regression-from-scratch/issues
Project-URL: Documentation, https://github.com/illo_one_go/linear-regression-from-scratch/docs
Keywords: machine-learning,linear-regression,education,numpy
Classifier: Development Status :: 3 - Alpha
Classifier: Intended Audience :: Education
Classifier: Intended Audience :: Science/Research
Classifier: License :: OSI Approved :: MIT License
Classifier: Operating System :: OS Independent
Classifier: Programming Language :: Python :: 3
Classifier: Programming Language :: Python :: 3.8
Classifier: Programming Language :: Python :: 3.9
Classifier: Programming Language :: Python :: 3.10
Classifier: Programming Language :: Python :: 3.11
Classifier: Topic :: Scientific/Engineering :: Artificial Intelligence
Classifier: Topic :: Education
Requires-Python: >=3.8
License-File: LICENSE
Requires-Dist: numpy>=1.21.0
Provides-Extra: dev
Requires-Dist: pytest>=7.0.0; extra == "dev"
Requires-Dist: pytest-cov>=4.0.0; extra == "dev"
Requires-Dist: black>=22.0.0; extra == "dev"
Requires-Dist: isort>=5.0.0; extra == "dev"
Requires-Dist: ruff>=0.1.0; extra == "dev"
Provides-Extra: notebooks
Requires-Dist: jupyter>=1.0.0; extra == "notebooks"
Requires-Dist: notebook>=6.4.0; extra == "notebooks"
Requires-Dist: matplotlib>=3.5.0; extra == "notebooks"
Requires-Dist: seaborn>=0.11.0; extra == "notebooks"
Requires-Dist: pandas>=1.3.0; extra == "notebooks"
Provides-Extra: docs
Requires-Dist: sphinx>=4.0.0; extra == "docs"
Requires-Dist: sphinx-rtd-theme>=1.0.0; extra == "docs"
Dynamic: license-file
